worldvision/__init__.py
worldvision/calculations.py
worldvision/camera.py
worldvision-0.0.11.dist-info/LICENSE.txt
worldvision-0.0.11.dist-info/METADATA
worldvision-0.0.11.dist-info/WHEEL
worldvision-0.0.11.dist-info/top_level.txt
worldvision-0.0.11.dist-info/RECORD
