Metadata-Version: 2.1
Name: worldvision
Version: 0.0.11
Summary: Calculate real world distance, angle, and more, just from the video/image
Author-email: Jatin Jain <jatin@exact.codes>
Maintainer-email: Jatin Jain <jatin@exact.codes>
License: MIT License
Project-URL: Homepage, https://github.com/heyJatin/worldvision
Project-URL: Bug Reports, https://github.com/heyJatin/worldvision/issues
Keywords: worldvision,math,geometry,distance,angle,speed,computer vision,vision,ai
Requires-Python: >=3.7
License-File: LICENSE.txt
Requires-Dist: python-math
